{
  "Url": "http://www.baomoi.com/Bay-khi-noi-loan-xai-vu-khi-khung-tan-pha-hanh-tinh/132/13553255.epi",
  "Time": "13/04/2014 16:16",
  "Title": "Bầy khỉ nổi loạn xài vũ khí 'khủng' tàn phá hành tinh",
  "Category": "Tin tức > Giải trí > Sân khấu - Điện ảnh",
  "Description": "Bộ ảnh mới từ 'Dawn of the Planet of the Apes' ('Bình minh của Hành tinh khỉ') cho thấy sự nổi loạn của bầy khỉ.",
  "Content": "<tr><td><div> <div> <div>Một số bức ảnh từ bộ phim giả tưởng <span>Dawn of the Planet of the Apes</span> (tựa Việt: <span>Bình minh của Hành tinh khỉ</span>) vừa được hãng 20th Century Fox tung ra qua tạp chí nổi tiếng USA Today. Trong hình, những chú khỉ nổi loạn ngày càng trở nên đáng sợ hơn, với súng ống lăm lăm chỉ chực bắn.</div> <div>  <div><span class='storyInlinePhoto'><img src='http://kenh14.vcmedia.vn/k:QuickNewsK14/4071215/2014/04/img_201404111630179014/bay-khi-noi-loan-xai-vu-khi-khung-tan-pha-hanh-tinh.jpg' ></span></div> <div>  <div><span class='storyInlinePhoto'><img src='http://kenh14.vcmedia.vn/k:QuickNewsK14/4071215/2014/04/img_201404111630180262/bay-khi-noi-loan-xai-vu-khi-khung-tan-pha-hanh-tinh.jpg' ></span></div> </div> </div>  <div>Một số bức ảnh khác cho thấy nỗi bực bội và cả sự sầu thảm của Caesar ( Andy Serkis <span>)</span>, kẻ cầm đầu bầy khỉ đột biến gen. Dưới sự chỉ đạo của Caesar, bầy khỉ di chuyển từng nhóm đông đúc. Ngạc nhiên nhất là không chỉ sử dụng súng, gậy gộc như người, chúng còn cưỡi cả ngựa. </div> <div>  <div><span class='storyInlinePhoto'><img src='http://kenh14.vcmedia.vn/k:QuickNewsK14/4071215/2014/04/img_201404111630105492/bay-khi-noi-loan-xai-vu-khi-khung-tan-pha-hanh-tinh.jpg' ></span></div> <div>  <div><span class='storyInlinePhoto'><img src='http://kenh14.vcmedia.vn/k:QuickNewsK14/4071215/2014/04/img_20140411163019477/bay-khi-noi-loan-xai-vu-khi-khung-tan-pha-hanh-tinh.jpg' ></span></div> </div>  </div> <div>Không chỉ có lũ khỉ, các nhân vật khác trong phim do Gary Oldman , Jason Clarke, và Keri Russell cũng xuất hiện trong bộ ảnh. Mặc dù sự căng thẳng hiện diện đầy rẫy mỗi khung hình của <span>Dawn of the Planet of the Apes</span>, nhưng trong bức ảnh cuối, người xem lại bất ngờ thấy một khoảnh khắc an bình hiếm có giữa người và khỉ.  <div><span class='storyInlinePhoto'><img src='http://kenh14.vcmedia.vn/k:QuickNewsK14/4071215/2014/04/img_201404111630131186/bay-khi-noi-loan-xai-vu-khi-khung-tan-pha-hanh-tinh.jpg' ></span></div> <div>  <div><span class='storyInlinePhoto'><img src='http://kenh14.vcmedia.vn/k:QuickNewsK14/4071215/2014/04/img_201404111630168718/bay-khi-noi-loan-xai-vu-khi-khung-tan-pha-hanh-tinh.jpg' ></span></div> </div> </div>  <div>Andy Serkis, nam diễn viên thể hiện vai Caesar, đã tiết lộ về nhân vật của mình: &quot;Caesar không chỉ có vợ mà còn có 2 cậu con trai. Bộ phim Dawn of the Planet of the Apes lần này xoay quanh giá trị gia đình và những gì bạn dám hy sinh để bảo vệ những người thân yêu, khi cuộc sống bị đe dọa&quot;.</div> <div>  <div> <div><span class='storyInlinePhoto'><img src='http://kenh14.vcmedia.vn/k:QuickNewsK14/4071215/2014/04/img_201404111630121046/bay-khi-noi-loan-xai-vu-khi-khung-tan-pha-hanh-tinh.jpg' ></span></div>  <div><span class='storyInlinePhoto'><img src='http://kenh14.vcmedia.vn/k:QuickNewsK14/4071215/2014/04/img_201404111630127488/bay-khi-noi-loan-xai-vu-khi-khung-tan-pha-hanh-tinh.jpg' ></span></div> </div> </div>  <div>Trong khi đó, đạo diễn Matt Reeves giải thích về việc những người sống sót sẽ làm gì trong <span>Dawn of the Planet of the Apes</span>: &quot;Những nhóm người nhỏ nhoi đấu tranh để trở lại cầm quyền còn loài khỉ thì chiến đấu cho sự sống còn. Câu hỏi lớn được đặt ra cho bộ phim là họ có thể cùng tồn tại hay không?&quot;  <div> <div><span class='storyInlinePhoto'><img src='http://kenh14.vcmedia.vn/k:QuickNewsK14/4071215/2014/04/img_201404111630206782/bay-khi-noi-loan-xai-vu-khi-khung-tan-pha-hanh-tinh.jpg' ></span></div>  <div><span class='storyInlinePhoto'><img src='http://kenh14.vcmedia.vn/k:QuickNewsK14/4071215/2014/04/img_201404111630114338/bay-khi-noi-loan-xai-vu-khi-khung-tan-pha-hanh-tinh.jpg' ></span></div> </div></div> <div>Phần tiếp theo của <span>Rise of the Planet of the Apes</span> năm 2011 là câu chuyện về quốc gia của loài khỉ tiến hóa do Caesar cầm đầu. Bầy khỉ bị đe dọa bởi một nhóm người còn sống sót sau sự tàn phá khủng khiếp của virus trước đó. Cả hai phe cố duy trì một nền hòa bình mong manh. Tuy nhiên, chỉ sau thời gian ngắn, cả hai bên bị đẩy đến bờ vực của một cuộc chiến tranh, nhằm xác định ai sẽ là người chiếm ưu thế trên Trái đất.</div>  <div><span>Dawn of the Planet of the Apes</span> (tựa Việt: <span>Bình minh của Hành tinh khỉ</span>) sẽ được phát hành tại các rạp của Mỹ vào ngày 11/7.</div> </div> </div><br /></td></tr>",
  "KeyWords": [
    "khỉ",
    "hành tinh",
    "Bình Minh",
    "nổi loạn",
    "bức ảnh",
    "cầm đầu",
    "bộ ảnh",
    "tàn phá",
    "khỉ đột",
    "Gary Oldman",
    "Twentieth Century Fox",
    "USA Today",
    "gene",
    "đạo diễn",
    "virus"
  ],
  "Trends": [
    {
      "word": "Amazon",
      "weith": "5"
    },
    {
      "word": "Angelababy",
      "weith": "5"
    },
    {
      "word": "Captain America",
      "weith": "2"
    },
    {
      "word": "Chiều Xuân",
      "weith": "6"
    },
    {
      "word": "cư dân mạng",
      "weith": "5"
    },
    {
      "word": "đạo diễn",
      "weith": "1"
    },
    {
      "word": "đoàn làm phim",
      "weith": "2"
    },
    {
      "word": "êkíp",
      "weith": "6"
    },
    {
      "word": "fan",
      "weith": "2"
    },
    {
      "word": "Jewel",
      "weith": "6"
    },
    {
      "word": "Kim Soo Hyun",
      "weith": "3"
    },
    {
      "word": "Lee Min Ho",
      "weith": "3"
    },
    {
      "word": "Minh Hằng",
      "weith": "2"
    },
    {
      "word": "Nhã Phương",
      "weith": "2"
    },
    {
      "word": "phim hài",
      "weith": "6"
    },
    {
      "word": "phim hoạt hình",
      "weith": "5"
    },
    {
      "word": "scandal",
      "weith": "5"
    },
    {
      "word": "showbiz",
      "weith": "3"
    },
    {
      "word": "The Avengers",
      "weith": "5"
    },
    {
      "word": "trailer",
      "weith": "3"
    },
    {
      "word": "Trần Lực",
      "weith": "1"
    },
    {
      "word": "Trần Thánh Tông",
      "weith": "2"
    },
    {
      "word": "Triệu Vy",
      "weith": "6"
    },
    {
      "word": "Trịnh Thịnh",
      "weith": "1"
    },
    {
      "word": "Truyền hình thực tế",
      "weith": "6"
    },
    {
      "word": "TVB",
      "weith": "6"
    },
    {
      "word": "Twilight",
      "weith": "5"
    },
    {
      "word": "video clip",
      "weith": "3"
    },
    {
      "word": "VTV3",
      "weith": "5"
    },
    {
      "word": "Vũ Ngọc Đãng",
      "weith": "3"
    }
  ]
}