{
  "Url": "http://www.baomoi.com/VLeague-ve-dau-sau-scandal-ban-do-cua-VNinh-Binh/87/13553094.epi",
  "Time": "13/04/2014 15:39",
  "Title": "V-League về đâu sau scandal bán độ của V.Ninh Bình",
  "Category": "Tin tức > Thể thao > Bóng đá",
  "Description": "(Soha.vn) - Vì bán độ, V.Ninh Bình sẽ rời V-League hoặc ở lại và bị trừ điểm. Dù theo hướng nào, CLB này cũng làm BXH giải quốc nội biến động mạnh.",
  "Content": "<tr><td><span class='storyInlinePhoto'><img src='http://sohanews2.vcmedia.vn/zoom/660_360/2014/1-56584-crop1397378302100p.jpg' ></span> <div> <p><span>Với scandal bán độ, dàn xếp tỷ số được cho là ở cả AFC Cup lẫn V-League, V.<strong> Ninh Bình </strong> đang đứng trước nguy cơ rất lớn sẽ giải tán đội bóng, bỏ ngang giải quốc nội 2014.</span></p> <p>Nếu điều này thật sự xảy ra, tiền lệ Sài Gòn Xuân Thành sẽ tái diễn. Kết quả 8 trận đã đấu của V.Ninh Bình sẽ bị hủy, làm V-League sau 12 vòng đấu bị biến động mạnh. Chắc chắn sẽ có rất nhiều tranh cãi xảy ra, khi mà CLB nào thua V.<strong> Ninh Bình </strong> thì sung sướng, còn các đội thắng hay hòa thì buồn bực vì mất điểm.</p> <p>Có thể điểm mặt các CLB sẽ không vui như Đồng Nai (2-2), Than Quảng Ninh (3-1), SHB Đà Nẵng (1-1), Đồng Tâm Long An (1-1), QNK Quảng Nam (3-1), Becamex Bình Dương (5-2) và Hùng Vương An Giang (2-2). Chỉ duy nhất Hà Nội T&amp;T là sung sướng khi đã thua V.Ninh Bình 1-3 ở vòng 3 V-League 2014.</p> <div type='Photo'> <div><span class='storyInlinePhoto'><img src='http://sohanews2.vcmedia.vn/2014/2-1397378260970.jpg' ></span></div> <div> <p>Phía sau scaldan bán độ của V. Ninh Bình sẽ là một mớ hỗn độn</p> </div> </div> <p>Theo một chiều hướng khác, ít tranh cãi hơn là V.Ninh Bình vẫn tiếp tục cuộc chơi nhưng có thể bị phạt nặng nếu cảnh sát xác nhận có tiêu cực ở V-League. CLB của bầu Trường khả năng sẽ bị phạt rất nhiều tiền và trừ điểm, thậm chí xuống hạng – cũng chẳng khác án phạt khi bỏ giải là mấy, nhưng không ảnh hưởng đến những CLB còn lại.</p> <p>Tuy nhiên khả năng này rất khó xảy ra, bởi đã có ít nhất 11 cầu thủ V.<strong> Ninh Bình </strong> thừa nhận bán độ ở AFC. Mà Chủ tịch VFF Lê Hùng Dũng thì đã xác nhận sẽ phạt cấm số cầu thủ này vĩnh viễn không được thi đấu bóng đá ở Việt Nam.</p> <p>Thêm vào đó, bầu Trường đã quá chán nản với các cầu thủ V.Ninh Bình, gần như mất hết tâm huyết tiếp tục làm bóng đá. Thế nên, viễn cảnh xuất hiện một Sài Gòn Xuân Thành thứ 2 chính thức bỏ giải gần như chắc chắn xảy ra và V-League lại một phen náo loạn, cãi vã…</p>  </div><br /></td></tr>",
  "KeyWords": [
    "Vinakansai Ninh Bình",
    "V-League",
    "bán độ",
    "Sài Gòn Xuân Thành",
    "phạt",
    "câu lạc bộ",
    "sung sướng",
    "scandal",
    "Soha",
    "cầu thủ",
    "tranh cãi",
    "Cúp AFC",
    "Đồng Nai",
    "Quảng Ninh",
    "SHB Đà Nẵng"
  ],
  "Trends": [
    {
      "word": "Alex Oxlade-Chamberlain",
      "weith": "6"
    },
    {
      "word": "Almeria",
      "weith": "4"
    },
    {
      "word": "Anfield",
      "weith": "5"
    },
    {
      "word": "Arsenal",
      "weith": "1"
    },
    {
      "word": "Arsene Wenger",
      "weith": "5"
    },
    {
      "word": "Atletico Madrid",
      "weith": "5"
    },
    {
      "word": "Barcelona",
      "weith": "1"
    },
    {
      "word": "Bayern",
      "weith": "4"
    },
    {
      "word": "Champions League",
      "weith": "2"
    },
    {
      "word": "Chelsea",
      "weith": "3"
    },
    {
      "word": "Cúp AFC",
      "weith": "3"
    },
    {
      "word": "Cúp FA",
      "weith": "3"
    },
    {
      "word": "Dortmund",
      "weith": "6"
    },
    {
      "word": "Everton",
      "weith": "6"
    },
    {
      "word": "Giải ngoại hạng Anh",
      "weith": "2"
    },
    {
      "word": "Granada",
      "weith": "3"
    },
    {
      "word": "Liên đoàn bóng đá châu Á",
      "weith": "6"
    },
    {
      "word": "Liên đoàn bóng đá Việt Nam",
      "weith": "5"
    },
    {
      "word": "Lionel Messi",
      "weith": "4"
    },
    {
      "word": "Liverpool",
      "weith": "1"
    },
    {
      "word": "Manchester City",
      "weith": "1"
    },
    {
      "word": "Manchester United",
      "weith": "3"
    },
    {
      "word": "Ninh Bình",
      "weith": "3"
    },
    {
      "word": "Per Mertesacker",
      "weith": "6"
    },
    {
      "word": "Primera Liga",
      "weith": "5"
    },
    {
      "word": "Real Madrid",
      "weith": "2"
    },
    {
      "word": "Thanh Hóa",
      "weith": "5"
    },
    {
      "word": "Vinakansai Ninh Bình",
      "weith": "1"
    },
    {
      "word": "V-League",
      "weith": "4"
    },
    {
      "word": "Wigan",
      "weith": "2"
    }
  ]
}