{
  "Url": "http://www.baomoi.com/Thuc-hu-khuc-duong-cua-co-hon-ma-bao-oan/141/13553370.epi",
  "Time": "13/04/2014 16:21",
  "Title": "Thực hư khúc đường cua có “hồn ma, báo oán”",
  "Category": "Tin tức > Pháp luật > An ninh - Trật tự",
  "Description": "Những 'vong hồn' xuất hiện để báo oán, gây ra những tai nạn thảm khốc.... là lời đồn khiến người yếu bóng vía sợ hãi đến rợn tóc gáy mỗi khi phải đi qua đoạn đường 'ma ám' này.",
  "Content": "<tr><td><div itemprop='articleBody'> Đó là đoạn khúc cua ngay trên con đường tỉnh lộ 419, chạy qua thôn Đồng Mít, xã Đồng Tâm, huyện Mỹ Đức, thành phố Hà Nội.<br><br><span> Muôn nẻo lời đồn</span><br><br> Có dịp đi trên tỉnh lộ 419, đoạn chạy qua thôn Đồng Mít, xã Đồng Tâm, huyện Mỹ Đức, thành phố Hà Nội, khách phương xa dễ thấy khi đến đoạn khúc đường cua hiện ngay trước mắt là ngôi miếu nhỏ ngày đêm đỏ đèn, nhang khói nằm ngay bên vệ đường. Về cảnh quan, đây là một đoạn đường đẹp, một bên là hàng cây xanh tốt, bên kia là dãy núi Rặng cao sừng sững. <br><br>Nhưng đoạn đường nơi đây lại có lời đồn từ nhiều năm về câu chuyện kỳ lạ với những cái chết &quot;bất đắc kỳ tử&quot; và chuyện một ngôi miếu &quot;thiêng&quot; luôn được người dân trong vùng sùng bái, kiêng nể. <br><br><div><span class='storyInlinePhoto'><img src='http://images.danviet.vn/Images/Uploaded/Share/2014/04/13/anh_12.jpg' ></span><br>Con đường &quot;ma ám&quot; với những câu chuyện ly kỳ.<br><br /></div> Người dân thôn Đồng Mít kể rằng: Vào thời điểm những năm 1945 – 1946 có nhiều người trong thôn và các địa phương lân cận chết đói, xác chất thành đống tại khúc cua trên đoạn đường này. Thêm vào đó, sau này do người ta khai thác đá ở núi Rặng, chủ yếu dùng để kè bờ sông, nấu vôi và nhiều vụ tai nạn do mất an toàn lao động đã xảy ra, cũng làm chết không ít người. <br><br>Chị Hồng và chị Tư đều ở xã Đồng Tâm , khi đang làm việc bị ngã từ trên núi xuống tử vong. Rồi vụ bà Vũ đi kiếm củi trên núi bị ngã mất mạng, hay một đôi vợ chồng do bất cẩn trong lao động nên ngã xuống lò vôi.... Chính từ những cái chết tương tự, trùng hợp nhẫu nhiên liên tiếp như vậy, mà người dân đồn đại đoạn đường này có ma ám và nặng âm khí?<br><br> Nhiều đêm, nhất là những đêm có mưa phùn, người dân còn nghe thấy tiếng khóc nức nở, những tiếng kêu ai oán, những tiếng hú rợn người, những ánh lửa vụt lóe sáng, tiếng thì thầm nhỏ to của đôi vợ chồng trẻ, rồi cả những tiếng kêu đói khát, xin ăn... phát ra từ núi Rặng, nghe rất ghê rợn.<br><br>Anh Trịnh Văn Thăng, người dân địa phương còn kể: “ Có lần tôi và gia đình chuẩn bị đi ngủ thì đứa con nhỏ cứ nằng nặc đòi bố phải đưa ra núi Rặng chơi và xem các cô các chú nấu vôi... khiến cả gia đình tôi phát hoảng, hú vía ”.<br><br><div><span class='storyInlinePhoto'><img src='http://images.danviet.vn/Images/Uploaded/Share/2014/04/13/anh_2.jpg' ></span><br>Ngôi miếu hình thành ngay vệ đường.<br></div><br> Còn anh Thắm, một người từng làm nghề xe ôm tại cung đường này kể: “ Có lần chở khách, khi tới khúc cua, một người con gái rất xinh vẫy xe xin đi nhờ. Khi đi được khoảng 300 m, em hỏi đi về đâu thì cô gái bảo: “ Về xóm 2 Đồng Mít, trước đây, khi còn sống em vẫn hay đi nhờ xe của anh mà”. Quay đầu lại thì không thấy cô gái ngồi sau nữa, tôi hoang mang lo sợ mất một tuần, rồi bỏ nghề xe ôm từ đó”.<br><br>Nhiều người dân địa phương không chỉ sợ khi nhắc đến góc cua “ma ám” này, mà còn khiếp sợ bởi những vụ tai nạn giao thông thảm khốc xảy ra liên tiếp trùng lặp đến kỳ lạ. Rồi cứ thế, những câu chuyện, lời đồn hình thành, được thêu dệt mang đậm màu sắc liêu trai, khiến người dân làng trên xóm dưới phải hoang mang. Và khi màn đêm buông xuống, nhiều người còn sợ, không dám đi qua đoạn đường cua vì cho là &quot;có ma&quot; này.<br><br><div><span class='storyInlinePhoto'><img src='http://images.danviet.vn/Images/Uploaded/Share/2014/04/13/anh_3.jpg' ></span><br>Đoạn khúc cua ngay bên ngôi miếu.<br></div><br> Anh Bảo, làm nghề rửa xe, sống gần khúc cua cho biết: “Mình sống gần đây, hầu như tai nạn nào cũng chứng kiến. Có một anh bộ đội ở tỉnh Thanh Hóa đang đi xe máy đến khúc cua này, dù đường vắng không có ai, vậy mà lại đâm vào cột mốc bên đường, tử vong tại chỗ”.<br><br>Còn anh H (xin được giấu tên) cũng kể lại: “Bác trưởng họ nhà em, mới ở trong miền Nam ra chơi, cùng vài người bạn khi đi về tới khúc cua, xe đi rất chậm vậy mà như có một bàn tay ma quái vô hình nào đó đẩy xe xuống vệ đường, đập đầu vào đá. Người nhà đưa đi cấp cứu tại bệnh viện Việt Đức, một tuần sau thì mất ”.<br><br><div><span class='storyInlinePhoto'><img src='http://images.danviet.vn/Images/Uploaded/Share/2014/04/13/anh_6.jpg' ></span></div><br>Theo ban công an xã Đồng Tâm, vài năm trước tại chính khúc cua này, năm nào cũng xảy ra hàng chục vụ tai nạn giao thông mà đa phần dẫn tới tử vong, số người sống sót sau tai nạn là rất ít. Nạn nhân chủ yếu bị chấn thương vùng đầu và nhiều người còn đang ở độ thanh niên trai tráng, tuổi từ 17 – 40, nạn nhân trung tuổi và là phụ nữ thì rất ít.<br><br>Quá khiếp sợ trước những hiện tượng trùng lắp xảy ra hết sức ngẫu nhiên như vậy nên các cụ cao niên tại thôn Đồng Mít đã xây một ngôi miếu tại chỗ khúc đường cua này để cầu siêu cho những người xấu số và cầu mong thượng lộ bình an cho những phương tiện tham gia giao thông khi qua đây.<br><br> Bác Lê Đình Quảng, chủ cửa hàng tạp hóa gần đó cho biết: “ Tôi không tin vào chuyện ma quỷ nhưng đoạn đường đó là khu đất rất thiêng, trước đây cũng có nhiều người chết với các nguyên nhân khác nhau. Kể từ khi ngôi miếu được xây dựng thì tai nạn giảm hẳn, mà có tai nạn thì cũng chỉ bị chấn thương nhẹ, không có vụ nào gây tử vong ”.<br><br><div><span class='storyInlinePhoto'><img src='http://images.danviet.vn/Images/Uploaded/Share/2014/04/13/anh_7.jpg' ></span></div><br> Về lời đồn khúc cua trên đoạn đường tại tỉnh lộ 419 bị “ma ám”, ông Nguyễn Văn Minh, trưởng công an Xã Đồng Tâm cho biết: “ Làm gì có những chuyện hoang đường đó. Đúng là từ khi xây miếu xong, tai nạn ít xảy ra, một phần cũng là yếu tố tâm linh của người dân, nhưng quan trọng hơn là người tham gia giao thông qua đây nhìn thấy miếu, nghĩ đến những vụ tai nạn trước mà có ý thức đi chậm lại”.<br><br>Theo ông Nguyễn Trọng Điệp – phó chủ tịch Ủy ban nhân dân xã Đồng Tâm: Lời đồn về khúc cua &quot;ma ám&quot; chỉ là do người dân thêu dệt. Chẳng hạn như trước đây trong lúc đêm tối một số người đi làm về qua khúc cua này thấy bóng người lập lờ nói năng lảm nhảm thì tưởng là ma hiện hình, nhưng thực ra đó là do một người đàn ông bị bệnh tâm thần điên loạn đi lang thang khắp thôn khiến mọi người nhầm tưởng.<br><br> Cũng theo ông Điệp: “Những vụ tai nạn giao thông xảy ra vài năm gần đây nguyên nhân là do đoạn đường này ít người qua lại, mặt đường nơi góc cua hẹp, lại bị rặng cây um tùm che khuất tầm nhìn, các phương tiện khi tham gia giao thông thường đi nhanh, tới góc cua không làm chủ được tay lái nên gây tai nạn”.<br><br> Ông Trần Quang Long – phó Bí thư xã Đồng Tâm cho biết: “Những tin đồn ma trêu, quỷ ám gì đó... là không có căn cứ, xã sẽ tuyên truyền để người dân hiểu rõ. Nguyên nhân chủ yếu của những vụ tai nạn là do ý thức của người tham gia giao thông kém, chạy quá tốc độ; thậm chí có vụ khi tham gia giao thông người điều khiển phương tiện đang trong tình trạng phê ma túy. Người dân địa phương không nên đồn đoán một cách suy diễn thiếu căn cứ, gây tâm lý không tốt trong nhân dân”.<br> </div> <p itemprop='author'>Trần Toản </p><br /></td></tr>",
  "KeyWords": [
    "khúc cua",
    "ma ám",
    "Đồng Tâm",
    "tai nạn",
    "lời đồn",
    "cua",
    "mít",
    "người dân",
    "giao thông",
    "tử vong",
    "tai nạn giao thông",
    "Mỹ Đức",
    "Hà Nội",
    "khai thác đá",
    "Thanh Hóa"
  ],
  "Trends": [
    {
      "word": "Bà Rịa Vũng Tàu",
      "weith": "1"
    },
    {
      "word": "Bắc Sơn",
      "weith": "4"
    },
    {
      "word": "Ban Chỉ huy quân sự",
      "weith": "3"
    },
    {
      "word": "Bệnh viện Chợ Rẫy",
      "weith": "1"
    },
    {
      "word": "Bình Tân",
      "weith": "6"
    },
    {
      "word": "Hà Tĩnh",
      "weith": "5"
    },
    {
      "word": "Hải An",
      "weith": "5"
    },
    {
      "word": "Hải Phòng",
      "weith": "3"
    },
    {
      "word": "Khánh Hòa",
      "weith": "4"
    },
    {
      "word": "Lexus",
      "weith": "5"
    },
    {
      "word": "Mai Dịch",
      "weith": "2"
    },
    {
      "word": "Nha Trang",
      "weith": "2"
    },
    {
      "word": "phòng cháy chữa cháy",
      "weith": "3"
    },
    {
      "word": "Phước Long",
      "weith": "6"
    },
    {
      "word": "Phương Trang",
      "weith": "4"
    },
    {
      "word": "Quận 1",
      "weith": "6"
    },
    {
      "word": "Quỳnh Lưu",
      "weith": "3"
    },
    {
      "word": "Sân bay Cát Bi",
      "weith": "4"
    },
    {
      "word": "Soha",
      "weith": "4"
    },
    {
      "word": "sông Sài Gòn",
      "weith": "2"
    },
    {
      "word": "Tân Thành",
      "weith": "1"
    },
    {
      "word": "Thạch Hà",
      "weith": "3"
    },
    {
      "word": "Thanh Hóa",
      "weith": "4"
    },
    {
      "word": "Thủ Đức",
      "weith": "1"
    },
    {
      "word": "Tiền Giang",
      "weith": "3"
    },
    {
      "word": "Trung Tự",
      "weith": "6"
    },
    {
      "word": "Tuy Phước",
      "weith": "6"
    },
    {
      "word": "video clip",
      "weith": "6"
    },
    {
      "word": "Võ Văn Kiệt",
      "weith": "6"
    },
    {
      "word": "xe đạp điện",
      "weith": "1"
    }
  ]
}