{
  "Url": "http://www.baomoi.com/Sap-xay-cau-can-Nhon--Kim-Ma-quy-mo-hon-64-trieu-USD/148/13544936.epi",
  "Time": "12/04/2014 10:00",
  "Title": "Sắp xây cầu cạn Nhổn - Kim Mã quy mô hơn 64 triệu USD",
  "Category": "Tin tức > Nhà đất > Đầu tư - Quy hoạch",
  "Description": "BizLIVE - Tuyến cầu cạn đi từ Nhổn về Kim Mã là dự án có quy mô vĩnh cửu, gồm 318 nhịp và 3 cầu vượt: Qua sông Nhuệ, cầu vượt vành đai 3 và vành đai 2.",
  "Content": "<tr><td><div> <div> <span class='storyInlinePhoto'><img src='http://bizlive.vn/Uploaded/tuanminh/2014_04_12/550ga_MPCZ.jpg?width=670&amp;height=350&amp;crop=auto' ></span><p>Đường sắt đô thị.</p> </div> <div> <p>Ban Quản lý dự án đường sắt đô thị Hà Nội và Nhà thầu Daelim (Hàn Quốc) vừa ký hợp đồng xây dựng gói thầu số 1 thuộc Dự án đường sắt đô thị thí điểm TP. Hà Nội tuyến số 3, đoạn từ Nhổn - Ga Hà Nội.</p> <p>Tuyến cầu cạn đi từ Nhổn về Kim Mã là dự án có quy mô vĩnh cửu, gồm 318 nhịp và 3 cầu vượt: Qua sông Nhuệ, cầu vượt vành đai 3 và vành đai 2.</p> <p>Theo thiết kế, toàn bộ kết cấu của công trình sẽ sử dụng bê tông cốt thép và loại bê tông cốt thép dự ứng lực để bảo đảm tính bền vững của dự án trong thời gian dài.</p> <p>Đại diện Ban quản lý dự án đường sắt đô thị Hà Nội cho biết: Tổng giá trị gói thầu số 1 này lên tới 64,8 triệu euro (tương đương khoảng 1.872 tỷ đồng), dự kiến gói thầu sẽ được khởi công trong tháng 7/2014 và hoàn thành sau 30 tháng.</p> <p> Tuyến đường sắt đô thị Nhổn - Ga Hà Nội có chiều dài 12,5km trong đó có 8,5km đi trên cao và 4km đi ngầm từ Kim Mã về ga Hà Nội; với 8 ga trên cao, 4 ga ngầm và 1 khu depot tại Nhổn.</p> <p>Quá trình thi công toàn dự án có tổng cộng 9 gói thầu chính gồm 5 gói thầu xây lắp, 4 gói thầu thiết bị. </p> <p>Tính đến thời điểm hiện tại, dự án đã triển khai thi công được 3 gói thầu: Gói số 2 (các ga trên cao), gói thầu số 4 (hạ tầng kỹ thuật khu depot), gói thầu số 5 (các công trình kiến trúc khu depot). </p> <p>Theo đánh giá của Ban quản lý dự án, đây là dự án giao thông trọng điểm của TP. Hà Nội, tăng cường năng lực giao thông công cộng cho thủ đô. </p> <p>Đặc biệt, khi gói thầu số 1 được hoàn thành và đưa vào sử dụng cùng với việc hoàn thiện các hạng mục của những gói thầu khác thuộc dự án, Hà Nội sẽ đáp ứng nhu cầu đi lại dọc theo hành lang Đông – Tây.</p>  </div>  </div><br /></td></tr>",
  "KeyWords": [
    "gói thầu",
    "Nhổn",
    "cầu cạn",
    "cầu vượt",
    "vành đai",
    "Kim Mã",
    "đường sắt",
    "đô thị",
    "ga Hà Nội",
    "dự án",
    "ban quản lý dự án",
    "Sông Nhuệ",
    "Hà Nội",
    "Hàn Quốc",
    "bê tông cốt thép"
  ],
  "Trends": [
    {
      "word": "ASIAD",
      "weith": "3"
    },
    {
      "word": "Ba Đình",
      "weith": "6"
    },
    {
      "word": "ban quản lý dự án",
      "weith": "6"
    },
    {
      "word": "bê tông cốt thép",
      "weith": "6"
    },
    {
      "word": "Bình Thuận",
      "weith": "3"
    },
    {
      "word": "Bộ Giao Thông Vận Tải",
      "weith": "3"
    },
    {
      "word": "Bộ Quốc Phòng",
      "weith": "6"
    },
    {
      "word": "Bộ Xây dựng",
      "weith": "1"
    },
    {
      "word": "Cầu Giấy",
      "weith": "3"
    },
    {
      "word": "Đăk Lăk",
      "weith": "3"
    },
    {
      "word": "Điện Biên Phủ",
      "weith": "6"
    },
    {
      "word": "đường Hồ Chí Minh",
      "weith": "3"
    },
    {
      "word": "ga Hà Nội",
      "weith": "3"
    },
    {
      "word": "hội đồng nhân dân",
      "weith": "6"
    },
    {
      "word": "Lê Văn Tám",
      "weith": "6"
    },
    {
      "word": "Long Thành",
      "weith": "6"
    },
    {
      "word": "Luật Đầu Tư",
      "weith": "6"
    },
    {
      "word": "Mê Linh",
      "weith": "6"
    },
    {
      "word": "Metro",
      "weith": "6"
    },
    {
      "word": "Nhổn",
      "weith": "3"
    },
    {
      "word": "Phú Hòa",
      "weith": "6"
    },
    {
      "word": "quản lý dự án",
      "weith": "1"
    },
    {
      "word": "Quảng Trạch",
      "weith": "6"
    },
    {
      "word": "Sách kỷ lục Guinness",
      "weith": "6"
    },
    {
      "word": "Sở Giao thông Vận tải",
      "weith": "1"
    },
    {
      "word": "Sông Hồng",
      "weith": "3"
    },
    {
      "word": "Thanh Xuân",
      "weith": "6"
    },
    {
      "word": "TP HCM",
      "weith": "1"
    },
    {
      "word": "trái phép",
      "weith": "3"
    },
    {
      "word": "Võ Nguyên Giáp",
      "weith": "6"
    }
  ]
}