{
  "Url": "http://www.baomoi.com/Arsenal-chat-vat-giai-con-khat-danh-hieu/87/13553304.epi",
  "Time": "13/04/2014 16:22",
  "Title": "Arsenal chật vật giải cơn khát danh hiệu",
  "Category": "Tin tức > Thể thao > Bóng đá",
  "Description": "Khi Santi Cazorla bước lên và thực hiện thành công quả 11m, mang tấm vé vào chung kết FA Cup cho Arsenal sau loạt đấu súng trước Wigan đêm qua, các CĐV của họ mới thở phào. Liệu cái dớp mỗi lần đứng trước cửa thiên đường có kết thúc với Pháo Thủ ở mùa giải năm nay?",
  "Content": "<tr><td><div> <div><span class='storyInlinePhoto'><img src='http://static.bongdaplus.vn/Assets/Media/2014/04/13/47/arsenal11.jpg' ></span><p>Arsenal cần bản lĩnh hơn trong những thời điểm quyết định</p></div> <div align='justify'><a href='http://media.bongdaplus.vn/xem-video/11/3548/wigan-athletic-1-1-arsenal-pen-2-4-ban-ket-fa-cup-2013-14.bdmedia'><span>VIDEO: Wigan Athletic 1-1 Arsenal (Pen: 2-4)</span></a></div><br /><div align='justify'><a href='http://media.bongdaplus.vn/xem-video/11/3548/wigan-athletic-1-1-arsenal-pen-2-4-ban-ket-fa-cup-2013-14.bdmedia'>Ở trận đấu đêm qua với Wigan</a>, dù trước một đối thủ đang chơi tại Championship, Arsenal vẫn cho thấy họ thường gặp dớp trong những trận đấu quan trọng như thế nào. Cầm bóng đến 62% thời lượng trận đấu, tung ra đến 27 cú sút về khung thành đối phương, Arsenal vẫn bị thủng lưới trước, và rồi phải mất đến hơn 120 phút để khuất phục đối thủ. Không phủ nhận Wigan đã chơi đầy quả cảm, nhưng tâm lý thiếu chắc chắn, chủ quan, và kém quyết liệt của Arsenal vô tình khiến đại diện Championship tỏ ra trội hơn ở một vài thời điểm.</div><br /><div align='justify'>Ở trận đấu với Wigan đêm qua, các CĐV Pháo Thủ có thể biện minh cho sự <a href='http://bongdaplus.vn/tin-bai/16/88007/arsenal-mat-ca-doi-hinh-o-tran-ban-ket-cup-fa.bdplus'>thiếu hụt lớn về nhân sự</a> là nguyên nhân dẫn đến sự thiếu nét trong lối chơi của đội nhà. Đã có tới 10 cầu thủ của Arsenal vắng mặt: Gibbs, Rosicky, Koscielny, Oezil, Wilshere, Walcott, Gnabry, Diaby, Bendtner, Flamini (treo giò). Nhưng chất lượng hàng thủ ngày một đi xuống của Arsenal cũng là vấn đề rất đáng lo ngại, điển hình là tình huống Mertesacker phạm lỗi dẫn đến quả 11m. </div><br /><div align='justify'><div align='center'><span class='storyInlinePhoto'><img src='http://static.bongdaplus.vn/Assets/Media/2014/04/13/47//arsenal1.jpg' ></span><br></div><br>Kể từ mùa giải 2004/05, thời điểm gần nhất mà Arsenal nếm trải cảm giác lên ngôi ở một giải đấu (FA Cup), đội bóng của HLV Arsene Wenger đã có 4 lần khác lần gục ngã ở những trận chung kết - khoảnh khắc đến gần vinh quang nhất của họ. Đau đớn nhất trong số đó chính là trận thua bạc nhược 1-2 trước một đội bóng Championship khác, Birmingham City, tại trận chung kết Cúp Liên Đoàn ở mùa giải 2010/11. Ở những lần còn lại, Arsenal tỏ ra thiếu bản lĩnh ở những trận thua trước Chelsea (Community Shield năm 2005, chung kết Cúp Liên Đoàn mùa 2006/07) và Barca (chung kết Champions League 2005/06).<br><br>Trong một ngày đẹp trời, sẽ không có bất kỳ nghi ngờ nào về sức mạnh của Arsenal, với sự nhiệt huyết và máu lửa trong lối chơi. Nhưng trong một ngày tệ hại, sự mong manh là điều mà Arsenal thể hiện rõ ràng nhất, trước bất kỳ đối thủ nào, ở bất kỳ đẳng cấp nào. Gặp Hull hoặc Sheffield ở trận chung kết FA Cup năm nay sẽ là cơ hội lớn để các Pháo Thủ chấm dứt cơn khát danh hiệu kéo dài 9 năm. Nhưng điều quan trọng là Arsenal cần phải giải quyết được vấn đề tâm lý của chính họ.</div>  </div><br /></td></tr>",
  "KeyWords": [
    "Arsenal",
    "Wigan",
    "chung kết",
    "pháo thủ",
    "Cúp FA",
    "mùa giải",
    "liên đoàn",
    "Santi Cazorla",
    "lối chơi",
    "bản lĩnh",
    "cổ động viên",
    "video",
    "thủng lưới",
    "Tomas Rosicky",
    "Mesut Özil"
  ],
  "Trends": [
    {
      "word": "Alex Oxlade-Chamberlain",
      "weith": "6"
    },
    {
      "word": "Almeria",
      "weith": "4"
    },
    {
      "word": "Anfield",
      "weith": "5"
    },
    {
      "word": "Arsenal",
      "weith": "1"
    },
    {
      "word": "Arsene Wenger",
      "weith": "5"
    },
    {
      "word": "Atletico Madrid",
      "weith": "5"
    },
    {
      "word": "Barcelona",
      "weith": "1"
    },
    {
      "word": "Bayern",
      "weith": "4"
    },
    {
      "word": "Champions League",
      "weith": "2"
    },
    {
      "word": "Chelsea",
      "weith": "3"
    },
    {
      "word": "Cúp AFC",
      "weith": "3"
    },
    {
      "word": "Cúp FA",
      "weith": "3"
    },
    {
      "word": "Dortmund",
      "weith": "6"
    },
    {
      "word": "Everton",
      "weith": "6"
    },
    {
      "word": "Giải ngoại hạng Anh",
      "weith": "2"
    },
    {
      "word": "Granada",
      "weith": "3"
    },
    {
      "word": "Liên đoàn bóng đá châu Á",
      "weith": "6"
    },
    {
      "word": "Liên đoàn bóng đá Việt Nam",
      "weith": "5"
    },
    {
      "word": "Lionel Messi",
      "weith": "4"
    },
    {
      "word": "Liverpool",
      "weith": "1"
    },
    {
      "word": "Manchester City",
      "weith": "1"
    },
    {
      "word": "Manchester United",
      "weith": "3"
    },
    {
      "word": "Ninh Bình",
      "weith": "3"
    },
    {
      "word": "Per Mertesacker",
      "weith": "6"
    },
    {
      "word": "Primera Liga",
      "weith": "5"
    },
    {
      "word": "Real Madrid",
      "weith": "2"
    },
    {
      "word": "Thanh Hóa",
      "weith": "5"
    },
    {
      "word": "Vinakansai Ninh Bình",
      "weith": "1"
    },
    {
      "word": "V-League",
      "weith": "4"
    },
    {
      "word": "Wigan",
      "weith": "2"
    }
  ]
}